pixcrypt/__init__.py
pixcrypt/_piximg.py
PixCrypt-1.1.0.dist-info/LICENSE
PixCrypt-1.1.0.dist-info/METADATA
PixCrypt-1.1.0.dist-info/WHEEL
PixCrypt-1.1.0.dist-info/top_level.txt
PixCrypt-1.1.0.dist-info/RECORD
