Metadata-Version: 2.1
Name: PixCrypt
Version: 1.1.0
Summary: Library for encrypting text into an image
Author: ALhorm
Author-email: gladkoam@gmail.com
Keywords: pixcrypt pillow image encryption python
Classifier: Programming Language :: Python :: 3.11
Classifier: License :: OSI Approved :: MIT License
Classifier: Operating System :: OS Independent
Requires-Python: >=3.10
License-File: LICENSE
Requires-Dist: pillow >=10.0.0
